hyperdrive/Algotrader.py
hyperdrive/Broker.py
hyperdrive/Constants.py
hyperdrive/DataSource.py
hyperdrive/Exchange.py
hyperdrive/FileOps.py
hyperdrive/History.py
hyperdrive/Storage.py
hyperdrive/TimeMachine.py
hyperdrive/Workflow.py
hyperdrive/__init__.py
forcepush-1.0.3.dist-info/LICENSE
forcepush-1.0.3.dist-info/METADATA
forcepush-1.0.3.dist-info/WHEEL
forcepush-1.0.3.dist-info/top_level.txt
forcepush-1.0.3.dist-info/RECORD
