Metadata-Version: 2.1
Name: forcepush
Version: 1.0.3
Summary: An algorithmic trading platform
Home-page: https://github.com/suchak1/hyperdrive
Author: Krish Suchak
Author-email: suchak.krish@gmail.com
License: UNKNOWN
Project-URL: Bug Reports, https://github.com/suchak1/hyperdrive/issues
Project-URL: Source, https://github.com/suchak1/hyperdrive
Platform: UNKNOWN
Requires-Python: >=3.7
Requires-Dist: auto-sklearn (==0.14.0)
Requires-Dist: boto3 (==1.19.7)
Requires-Dist: cryptography (==35.0.0)
Requires-Dist: pandas (==1.3.4)
Requires-Dist: polygon-api-client (==0.2.11)
Requires-Dist: python-binance (==1.0.15)
Requires-Dist: python-dotenv (==0.19.1)
Requires-Dist: pytz (==2021.3)
Requires-Dist: robin-stocks (==2.1.0)
Requires-Dist: scikit-learn (==0.24.2)
Requires-Dist: scipy (==1.7.1)
Requires-Dist: ta (==0.7.0)
Requires-Dist: vectorbt (==0.21.0)
